{
	"classify001":{
		"name":"限时抢购",
		"list":[
					{
						"id":"shop01",
						"src":"1.jpg",
						"name":"鲜花速递  香槟玫瑰紫桔梗礼盒",
						"price":"256"
					},
					{
						"id":"shop02",						
						"src":"2.jpg",
						"name":"鲜花速递  香槟玫瑰紫桔梗礼盒",
						"price":"256"
					},
					{
						"id":"shop03",						
						"src":"3.jpg",
						"name":"鲜花速递  香槟玫瑰紫桔梗礼盒",
						"price":"256"
					},
					{
						"id":"shop04",
						
						"src":"4.jpg",
						"name":"鲜花速递  香槟玫瑰紫桔梗礼盒",
						"price":"256"
					},
					{
						"id":"shop05",						
						"src":"5.jpg",
						"name":"鲜花速递  香槟玫瑰紫桔梗礼盒",
						"price":"256"
					},
					{
						"id":"shop06",						
						"src":"6.jpg",
						"name":"鲜花速递  香槟玫瑰紫桔梗礼盒",
						"price":"256"
					},
					{
						"id":"shop07",						
						"src":"7.jpg",
						"name":"鲜花速递 香槟玫瑰紫桔梗礼盒",
						"price":"256"
					},
					{
						"id":"shop08",						
						"src":"8.jpg",
						"name":"鲜花速递 香槟玫瑰紫桔梗礼盒",
						"price":"256"
					},
					{
						"id":"shop09",
						"src":"9.jpg",
						"name":"鲜花速递 香槟玫瑰紫桔梗礼盒",
						"price":"256"
					},
					{
						"id":"shop10",
						"src":"10.jpg",
						"name":"鲜花速递 香槟玫瑰紫桔梗礼盒",
						"price":"256"
					}
		]
	},
	"classify002":{
		"name":"热卖促销",
		"list":[				
					{
						"id":"shop11",
						"src":"11.jpg",
						"name":"鲜花速递 香槟玫瑰紫桔梗礼盒",
						"price":"256"
					},
					{
						"id":"shop12",
						"src":"12.jpg",
						"name":"鲜花速递 香槟玫瑰紫桔梗礼盒",
						"price":"256"
					},
					{
						"id":"shop13",
						"src":"13.jpg",
						"name":"鲜花速递 香槟玫瑰紫桔梗礼盒",
						"price":"256"
					},
					{
						"id":"shop04",
						"src":"14.jpg",
						"name":"鲜花速递 香槟玫瑰紫桔梗礼盒",
						"price":"256"
					},
					{
						"id":"shop15",
						"src":"15.jpg",
						"name":"鲜花速递 香槟玫瑰紫桔梗礼盒",
						"price":"256"
					},
					{
						"id":"shop16",
						"src":"16.jpg",
						"name":"鲜花速递 香槟玫瑰紫桔梗礼盒",
						"price":"256"
					},
					{
						"id":"shop17",
						"src":"17.jpg",
						"name":"鲜花速递 香槟玫瑰紫桔梗礼盒",
						"price":"256"
					},
					{
						"id":"shop08",
						"src":"18.jpg",
						"name":"鲜花速递 香槟玫瑰紫桔梗礼盒",
						"price":"256"
					},
					{
						"id":"shop09",
						"src":"19.jpg",
						"name":"鲜花速递 香槟玫瑰紫桔梗礼盒",
						"price":"256"
					},
					{
						"id":"shop20",
						"src":"20.jpg",
						"name":"鲜花速递  香槟玫瑰紫桔梗礼盒",
						"price":"256"
					},
					{
						"id":"shop21",
						"src":"21.jpg",
						"name":"鲜花速递  香槟玫瑰紫桔梗礼盒",
						"price":"256"
					},
					{
						"id":"shop22",
						"src":"22.jpg",
						"name":"鲜花速递  香槟玫瑰紫桔梗礼盒",
						"price":"256"
					},
					{
						"id":"shop23",
						"src":"23.jpg",
						"name":"鲜花速递  香槟玫瑰紫桔梗礼盒",
						"price":"256"
					},
					{
						"id":"shop24",
						"src":"24.jpg",
						"name":"鲜花速递  香槟玫瑰紫桔梗礼盒",
						"price":"256"
					},
					{
						"id":"shop25",
						"src":"25.jpg",
						"name":"鲜花速递  香槟玫瑰紫桔梗礼盒",
						"price":"256"
					},
					{
						"id":"shop26",
						"src":"26.jpg",
						"name":"鲜花速递  香槟玫瑰紫桔梗礼盒",
						"price":"256"
					}
		]
	}
}
